Metadata-Version: 1.1
Name: ntc-websms
Version: 0.1.0
Summary: Commandline tool to send free SMS via http://www.meet.net.np
Home-page: https://github.com/sandipbgt/ntc-websms
Author: Sandip Bhagat
Author-email: sandipbgt@gmail.com
License: UNKNOWN
Platform: UNKNOWN
Classifier: Environment :: Console
Classifier: Programming Language :: Python :: 3
